faraway/__init__.py
faraway/datasets/__init__.py
faraway/datasets/aatemp/__init__.py
faraway/datasets/aatemp/aatemp.csv.bz2
faraway/datasets/abrasion/__init__.py
faraway/datasets/abrasion/abrasion.csv.bz2
faraway/datasets/air/__init__.py
faraway/datasets/air/air.csv.bz2
faraway/datasets/alfalfa/__init__.py
faraway/datasets/alfalfa/alfalfa.csv.bz2
faraway/datasets/anaesthetic/__init__.py
faraway/datasets/anaesthetic/anaesthetic.csv.bz2
faraway/datasets/butterfat/__init__.py
faraway/datasets/butterfat/butterfat.csv.bz2
faraway/datasets/cars/__init__.py
faraway/datasets/cars/cars.csv.bz2
faraway/datasets/cheddar/__init__.py
faraway/datasets/cheddar/cheddar.csv.bz2
faraway/datasets/chmiss/__init__.py
faraway/datasets/chmiss/chmiss.csv.bz2
faraway/datasets/chredlin/__init__.py
faraway/datasets/chredlin/chredlin.csv.bz2
faraway/datasets/clot/__init__.py
faraway/datasets/clot/clot.csv.bz2
faraway/datasets/coagulation/__init__.py
faraway/datasets/coagulation/coagulation.csv.bz2
faraway/datasets/composite/__init__.py
faraway/datasets/composite/composite.csv.bz2
faraway/datasets/cornnit/__init__.py
faraway/datasets/cornnit/cornnit.csv.bz2
faraway/datasets/corrosion/__init__.py
faraway/datasets/corrosion/corrosion.csv.bz2
faraway/datasets/crawl/__init__.py
faraway/datasets/crawl/crawl.csv.bz2
faraway/datasets/denim/__init__.py
faraway/datasets/denim/denim.csv.bz2
faraway/datasets/divusa/__init__.py
faraway/datasets/divusa/divusa.csv.bz2
faraway/datasets/eco/__init__.py
faraway/datasets/eco/eco.csv.bz2
faraway/datasets/eggprod/__init__.py
faraway/datasets/eggprod/eggprod.csv.bz2
faraway/datasets/families/__init__.py
faraway/datasets/families/families.csv.bz2
faraway/datasets/fat/__init__.py
faraway/datasets/fat/fat.csv.bz2
faraway/datasets/fortune/__init__.py
faraway/datasets/fortune/fortune.csv.bz2
faraway/datasets/fpe/__init__.py
faraway/datasets/fpe/fpe.csv.bz2
faraway/datasets/fruitfly/__init__.py
faraway/datasets/fruitfly/fruitfly.csv.bz2
faraway-0.0.6.dist-info/METADATA
faraway-0.0.6.dist-info/WHEEL
faraway-0.0.6.dist-info/top_level.txt
faraway-0.0.6.dist-info/RECORD
