Metadata-Version: 2.1
Name: faraway
Version: 0.0.6
Summary: Datasets and utilities to support books by Julian Faraway
Home-page: https://github.com/julianfaraway/LMP
Author: Julian Faraway
Author-email: jjf23@bath.ac.uk
License: UNKNOWN
Platform: UNKNOWN
Classifier: Programming Language :: Python :: 3
Classifier: License :: OSI Approved :: MIT License
Classifier: Operating System :: OS Independent
